{
	"name": "MSD research group",
	"title": "Modeling and Data Science",
	"abstract": "The MSD research group is part of the <a href='https://www.irimas.uha.fr' target='_blank'>IRIMAS Institute</a> from <a href='https://www.uha.fr/en/index.html' target='_blank'>Université de Haute-Alsace</a>, in Mulhouse. The research carried out by the MSD team concerns modeling and data science and focuses on theories and algorithms for extracting knowledge from large masses of data, generated by computer systems. Our work is in the fields of artificial intelligence, machine learning, data mining, big data and deep learning. In particular, our group has specific skills in the analysis of time series.",
	"image": "imgs/msd.png",
	"keywords": ["artificial intelligence", "data science", "machine learning", "deep learning", "time series", "medical images", "human motion"]
}
